arneso_poetry_publish_test/__init__.py
arneso_poetry_publish_test/__main__.py
arneso_poetry_publish_test/py.typed
arneso_poetry_publish_test-0.1.10.dist-info/LICENSE
arneso_poetry_publish_test-0.1.10.dist-info/WHEEL
arneso_poetry_publish_test-0.1.10.dist-info/METADATA
arneso_poetry_publish_test-0.1.10.dist-info/entry_points.txt
arneso_poetry_publish_test-0.1.10.dist-info/RECORD
