Metadata-Version: 2.1
Name: arneso-poetry-publish-test
Version: 0.1.10
Summary: Arneso Poetry Publish Test
Home-page: https://github.com/arneso-ssb/arneso-poetry-publish-test
License: MIT
Author: Arne Sørli
Author-email: 81353974+arneso-ssb@users.noreply.github.com
Requires-Python: >=3.8.1,<3.12
Classifier: Development Status :: 3 - Alpha
Classifier: License :: OSI Approved :: MIT License
Classifier: Programming Language :: Python :: 3
Classifier: Programming Language :: Python :: 3.9
Classifier: Programming Language :: Python :: 3.10
Classifier: Programming Language :: Python :: 3.11
Requires-Dist: click (>=8.1.3)
Project-URL: Changelog, https://github.com/arneso-ssb/arneso-poetry-publish-test/releases
Project-URL: Documentation, https://arneso-poetry-publish-test.readthedocs.io
Project-URL: Repository, https://github.com/arneso-ssb/arneso-poetry-publish-test
